agent_flow_craft-2025.4.1.1.dist-info/licenses/LICENSE
src/__init__.py
src/agents/__init__.py
src/agents/agent_concept_generation.py
src/agents/agent_feature_concept.py
src/agents/agent_feature_coordinator.py
src/agents/agent_feature_creation.py
src/agents/agent_github_integration.py
src/agents/agent_plan_validator.py
src/agents/agent_python_refactor.py
src/agents/agent_tdd_criteria.py
src/agents/base_agent.py
src/agents/context_manager.py
src/agents/local_agent_runner.py
src/agents/guardrails/__init__.py
src/agents/guardrails/out_guardrail_concept_generation_agent.py
src/agents/guardrails/out_guardrail_tdd_criteria_agent.py
src/cli/__init__.py
src/cli/cli.py
src/configs/__init__.py
src/core/__init__.py
src/core/agent_factory.py
src/core/logger.py
src/core/utils.py
src/core/settings/__init__.py
src/core/settings/agents.py
src/core/settings/common.py
src/core/utils/__init__.py
src/core/utils/data_masking.py
src/core/utils/env.py
src/core/utils/logger.py
src/core/utils/model_manager.py
src/core/utils/token_validator.py
src/core/utils/version_analyzer.py
src/scripts/__init__.py
src/scripts/run_agent_feature_coordinator.py
src/scripts/run_agent_github_integration.py
src/scripts/run_agent_python_refactor.py
src/scripts/util_clean_pycache.py
src/scripts/util_generate_docs_index.py
src/scripts/util_generate_tree.py
src/scripts/util_test_refactor_file_ops.py
src/scripts/util_update_imports.py
agent_flow_craft-2025.4.1.1.dist-info/METADATA
agent_flow_craft-2025.4.1.1.dist-info/WHEEL
agent_flow_craft-2025.4.1.1.dist-info/entry_points.txt
agent_flow_craft-2025.4.1.1.dist-info/top_level.txt
agent_flow_craft-2025.4.1.1.dist-info/RECORD
