Metadata-Version: 2.4
Name: agent-flow-craft
Version: 2025.4.1.1
Summary: Framework para automação de fluxo de criação de features usando agentes de IA
Author: Seu Nome
Author-email: seu.email@exemplo.com
Classifier: Development Status :: 3 - Alpha
Classifier: Intended Audience :: Developers
Classifier: License :: OSI Approved :: MIT License
Classifier: Operating System :: OS Independent
Classifier: Programming Language :: Python :: 3
Classifier: Programming Language :: Python :: 3.9
Classifier: Programming Language :: Python :: 3.10
Classifier: Programming Language :: Python :: 3.11
Classifier: Topic :: Software Development :: Libraries :: Python Modules
Requires-Python: >=3.9
License-File: LICENSE
Requires-Dist: openai>=1.0.0
Requires-Dist: openrouter>=0.3.0
Requires-Dist: google-generativeai>=0.3.0
Requires-Dist: rope>=1.10.0
Requires-Dist: pygithub>=2.1.0
Requires-Dist: python-dotenv>=1.0.0
Requires-Dist: rich>=13.0.0
Requires-Dist: typer>=0.9.0
Requires-Dist: pydantic>=2.0.0
Requires-Dist: requests>=2.31.0
Requires-Dist: tenacity>=8.2.0
Requires-Dist: cachetools>=5.3.0
Requires-Dist: pytest>=7.0.0
Requires-Dist: pytest-cov>=4.1.0
Requires-Dist: black>=23.0.0
Requires-Dist: isort>=5.12.0
Requires-Dist: flake8>=6.1.0
Requires-Dist: mypy>=1.5.0
Requires-Dist: autoflake>=2.2.0
Requires-Dist: commitizen>=3.12.0
Dynamic: author
Dynamic: author-email
Dynamic: classifier
Dynamic: description
Dynamic: description-content-type
Dynamic: license-file
Dynamic: requires-dist
Dynamic: requires-python
Dynamic: summary
